MANIFEST.in
README.rst
setup.py
addlyrics/__init__.py
addlyrics/__main__.py
addlyrics/addlyrics.py
addlyrics.egg-info/PKG-INFO
addlyrics.egg-info/SOURCES.txt
addlyrics.egg-info/dependency_links.txt
addlyrics.egg-info/entry_points.txt
addlyrics.egg-info/requires.txt
addlyrics.egg-info/top_level.txt